cd4py/__init__.py
cd4py/__main__.py
cd4py/lib.py
cd4py/pytokenizer.py
cd4py-0.1.0.dist-info/LICENSE
cd4py-0.1.0.dist-info/METADATA
cd4py-0.1.0.dist-info/WHEEL
cd4py-0.1.0.dist-info/entry_points.txt
cd4py-0.1.0.dist-info/top_level.txt
cd4py-0.1.0.dist-info/RECORD
