Metadata-Version: 2.1
Name: cd4py
Version: 0.1.0
Summary: CD4Py: Code De-Duplication for Python
Home-page: https://github.com/saltudelft/CD4Py
Author: Amir M. Mir (TU Delft)
Author-email: mir-am@hotmail.com
License: UNKNOWN
Keywords: python source code de-duplication detection cd4py
Platform: UNKNOWN
Classifier: License :: OSI Approved :: GNU General Public License v3 (GPLv3)
Classifier: Environment :: Console
Classifier: Programming Language :: Python
Classifier: Programming Language :: Python :: 3.5
Classifier: Programming Language :: Python :: 3.6
Classifier: Programming Language :: Python :: 3.7
Classifier: Operating System :: Unix
Classifier: Operating System :: MacOS
Classifier: Operating System :: POSIX
Classifier: Intended Audience :: Science/Research
Classifier: Topic :: Scientific/Engineering :: Artificial Intelligence
Classifier: Topic :: Software Development :: Libraries :: Python Modules
Requires-Dist: dpu-utils
Requires-Dist: tqdm
Requires-Dist: joblib
Requires-Dist: pandas
Requires-Dist: scikit-learn
Requires-Dist: numpy
Requires-Dist: annoy
